{"v":"5.7.1","fr":30,"ip":0,"op":91,"w":312,"h":350,"nm":"limpiar","ddd":0,"assets":[],"layers":[{"ddd":0,"ind":1,"ty":4,"nm":"Capa 4/Iconos_limpios contornos 4","sr":1,"ks":{"o":{"a":0,"k":100,"ix":11},"r":{"a":0,"k":0,"ix":10},"p":{"a":0,"k":[164,177,0],"ix":2},"a":{"a":0,"k":[110,169.5,0],"ix":1},"s":{"a":0,"k":[100,100,100],"ix":6}},"ao":0,"shapes":[{"ty":"gr","it":[{"ind":0,"ty":"sh","ix":1,"ks":{"a":0,"k":{"i":[[0,-0.915],[0.915,0],[0,0.915],[-0.914,0]],"o":[[0,0.915],[-0.914,0],[0,-0.915],[0.915,0]],"v":[[1.657,0],[-0.001,1.657],[-1.657,0],[-0.001,-1.657]],"c":true},"ix":2},"nm":"Trazado 1","mn":"ADBE Vector Shape - Group","hd":false},{"ty":"st","c":{"a":0,"k":[1,1,1,1],"ix":3},"o":{"a":0,"k":100,"ix":4},"w":{"a":0,"k":1,"ix":5},"lc":2,"lj":2,"bm":0,"nm":"Trazo 1","mn":"ADBE Vector Graphic - Stroke","hd":false},{"ty":"tr","p":{"a":0,"k":[75.756,4.157],"ix":2},"a":{"a":0,"k":[0,0],"ix":1},"s":{"a":1,"k":[{"i":{"x":[0.667,0.667],"y":[1,1]},"o":{"x":[0.167,0.167],"y":[0.167,0.167]},"t":38,"s":[0,0],"e":[100,100]},{"i":{"x":[0.667,0.667],"y":[1,1]},"o":{"x":[0.167,0.167],"y":[0.167,0.167]},"t":46.863,"s":[100,100],"e":[68.909,68.909]},{"i":{"x":[0.667,0.667],"y":[1,1]},"o":{"x":[0.333,0.333],"y":[0,0]},"t":57.698,"s":[68.909,68.909],"e":[100,100]},{"i":{"x":[0.667,0.667],"y":[1,1]},"o":{"x":[0.333,0.333],"y":[0,0]},"t":69.517,"s":[100,100],"e":[68.909,68.909]},{"i":{"x":[0.667,0.667],"y":[1,1]},"o":{"x":[0.333,0.333],"y":[0,0]},"t":79.366,"s":[68.909,68.909],"e":[100,100]},{"t":91}],"ix":3},"r":{"a":0,"k":0,"ix":6},"o":{"a":0,"k":100,"ix":7},"sk":{"a":0,"k":0,"ix":4},"sa":{"a":0,"k":0,"ix":5},"nm":"Transformar"}],"nm":"Grupo 1","np":2,"cix":2,"bm":0,"ix":1,"mn":"ADBE Vector Group","hd":false},{"ty":"gr","it":[{"ind":0,"ty":"sh","ix":1,"ks":{"a":0,"k":{"i":[[0,-1.757],[1.758,0],[0,1.757],[-1.756,0]],"o":[[0,1.757],[-1.756,0],[0,-1.757],[1.758,0]],"v":[[3.182,0],[-0.001,3.181],[-3.182,0],[-0.001,-3.181]],"c":true},"ix":2},"nm":"Trazado 1","mn":"ADBE Vector Shape - Group","hd":false},{"ty":"st","c":{"a":0,"k":[1,1,1,1],"ix":3},"o":{"a":0,"k":100,"ix":4},"w":{"a":0,"k":1,"ix":5},"lc":2,"lj":2,"bm":0,"nm":"Trazo 1","mn":"ADBE Vector Graphic - Stroke","hd":false},{"ty":"tr","p":{"a":0,"k":[55.446,58.785],"ix":2},"a":{"a":0,"k":[0,0],"ix":1},"s":{"a":1,"k":[{"i":{"x":[0.667,0.667],"y":[1,1]},"o":{"x":[0.167,0.167],"y":[0.167,0.167]},"t":32,"s":[0,0],"e":[100,100]},{"i":{"x":[0.667,0.667],"y":[1,1]},"o":{"x":[0.167,0.167],"y":[0.167,0.167]},"t":41.866,"s":[100,100],"e":[68.909,68.909]},{"i":{"x":[0.667,0.667],"y":[1,1]},"o":{"x":[0.333,0.333],"y":[0,0]},"t":53.929,"s":[68.909,68.909],"e":[100,100]},{"i":{"x":[0.667,0.667],"y":[1,1]},"o":{"x":[0.333,0.333],"y":[0,0]},"t":67.085,"s":[100,100],"e":[68.909,68.909]},{"i":{"x":[0.667,0.667],"y":[1,1]},"o":{"x":[0.333,0.333],"y":[0,0]},"t":78.049,"s":[68.909,68.909],"e":[100,100]},{"t":91}],"ix":3},"r":{"a":0,"k":0,"ix":6},"o":{"a":0,"k":100,"ix":7},"sk":{"a":0,"k":0,"ix":4},"sa":{"a":0,"k":0,"ix":5},"nm":"Transformar"}],"nm":"Grupo 2","np":2,"cix":2,"bm":0,"ix":2,"mn":"ADBE Vector Group","hd":false},{"ty":"gr","it":[{"ty":"gr","it":[{"ind":0,"ty":"sh","ix":1,"ks":{"a":0,"k":{"i":[[0,0],[0,0]],"o":[[0,0],[0,0]],"v":[[41.631,18.5],[50.91,18.5]],"c":false},"ix":2},"nm":"Trazado 1","mn":"ADBE Vector Shape - Group","hd":false},{"ty":"st","c":{"a":0,"k":[1,1,1,1],"ix":3},"o":{"a":0,"k":100,"ix":4},"w":{"a":0,"k":1,"ix":5},"lc":2,"lj":2,"bm":0,"nm":"Trazo 1","mn":"ADBE Vector Graphic - Stroke","hd":false},{"ty":"tr","p":{"a":0,"k":[0,0],"ix":2},"a":{"a":0,"k":[0,0],"ix":1},"s":{"a":0,"k":[100,100],"ix":3},"r":{"a":0,"k":0,"ix":6},"o":{"a":0,"k":100,"ix":7},"sk":{"a":0,"k":0,"ix":4},"sa":{"a":0,"k":0,"ix":5},"nm":"Transformar"}],"nm":"Grupo 3","np":2,"cix":2,"bm":0,"ix":1,"mn":"ADBE Vector Group","hd":false},{"ty":"gr","it":[{"ind":0,"ty":"sh","ix":1,"ks":{"a":0,"k":{"i":[[0,0],[0,0]],"o":[[0,0],[0,0]],"v":[[59.983,18.5],[69.262,18.5]],"c":false},"ix":2},"nm":"Trazado 1","mn":"ADBE Vector Shape - Group","hd":false},{"ty":"st","c":{"a":0,"k":[1,1,1,1],"ix":3},"o":{"a":0,"k":100,"ix":4},"w":{"a":0,"k":1,"ix":5},"lc":2,"lj":2,"bm":0,"nm":"Trazo 1","mn":"ADBE Vector Graphic - Stroke","hd":false},{"ty":"tr","p":{"a":0,"k":[0,0],"ix":2},"a":{"a":0,"k":[0,0],"ix":1},"s":{"a":0,"k":[100,100],"ix":3},"r":{"a":0,"k":0,"ix":6},"o":{"a":0,"k":100,"ix":7},"sk":{"a":0,"k":0,"ix":4},"sa":{"a":0,"k":0,"ix":5},"nm":"Transformar"}],"nm":"Grupo 4","np":2,"cix":2,"bm":0,"ix":2,"mn":"ADBE Vector Group","hd":false},{"ty":"gr","it":[{"ind":0,"ty":"sh","ix":1,"ks":{"a":0,"k":{"i":[[0,0],[0,0]],"o":[[0,0],[0,0]],"v":[[55.446,4.685],[55.446,13.964]],"c":false},"ix":2},"nm":"Trazado 1","mn":"ADBE Vector Shape - Group","hd":false},{"ty":"st","c":{"a":0,"k":[1,1,1,1],"ix":3},"o":{"a":0,"k":100,"ix":4},"w":{"a":0,"k":1,"ix":5},"lc":2,"lj":2,"bm":0,"nm":"Trazo 1","mn":"ADBE Vector Graphic - Stroke","hd":false},{"ty":"tr","p":{"a":0,"k":[0,0],"ix":2},"a":{"a":0,"k":[0,0],"ix":1},"s":{"a":0,"k":[100,100],"ix":3},"r":{"a":0,"k":0,"ix":6},"o":{"a":0,"k":100,"ix":7},"sk":{"a":0,"k":0,"ix":4},"sa":{"a":0,"k":0,"ix":5},"nm":"Transformar"}],"nm":"Grupo 5","np":2,"cix":2,"bm":0,"ix":3,"mn":"ADBE Vector Group","hd":false},{"ty":"gr","it":[{"ind":0,"ty":"sh","ix":1,"ks":{"a":0,"k":{"i":[[0,0],[0,0]],"o":[[0,0],[0,0]],"v":[[55.446,23.037],[55.446,32.316]],"c":false},"ix":2},"nm":"Trazado 1","mn":"ADBE Vector Shape - Group","hd":false},{"ty":"st","c":{"a":0,"k":[1,1,1,1],"ix":3},"o":{"a":0,"k":100,"ix":4},"w":{"a":0,"k":1,"ix":5},"lc":2,"lj":2,"bm":0,"nm":"Trazo 1","mn":"ADBE Vector Graphic - Stroke","hd":false},{"ty":"tr","p":{"a":0,"k":[0,0],"ix":2},"a":{"a":0,"k":[0,0],"ix":1},"s":{"a":0,"k":[100,100],"ix":3},"r":{"a":0,"k":0,"ix":6},"o":{"a":0,"k":100,"ix":7},"sk":{"a":0,"k":0,"ix":4},"sa":{"a":0,"k":0,"ix":5},"nm":"Transformar"}],"nm":"Grupo 6","np":2,"cix":2,"bm":0,"ix":4,"mn":"ADBE Vector Group","hd":false},{"ty":"tr","p":{"a":0,"k":[55.446,18.5],"ix":2},"a":{"a":0,"k":[55.446,18.5],"ix":1},"s":{"a":1,"k":[{"i":{"x":[0.667,0.667],"y":[1,1]},"o":{"x":[0.167,0.167],"y":[0.167,0.167]},"t":35,"s":[0,0],"e":[100,100]},{"i":{"x":[0.667,0.667],"y":[1,1]},"o":{"x":[0.167,0.167],"y":[0.167,0.167]},"t":44.365,"s":[100,100],"e":[68.909,68.909]},{"i":{"x":[0.667,0.667],"y":[1,1]},"o":{"x":[0.333,0.333],"y":[0,0]},"t":55.813,"s":[68.909,68.909],"e":[100,100]},{"i":{"x":[0.667,0.667],"y":[1,1]},"o":{"x":[0.333,0.333],"y":[0,0]},"t":68.301,"s":[100,100],"e":[68.909,68.909]},{"i":{"x":[0.667,0.667],"y":[1,1]},"o":{"x":[0.333,0.333],"y":[0,0]},"t":78.708,"s":[68.909,68.909],"e":[100,100]},{"t":91}],"ix":3},"r":{"a":0,"k":0,"ix":6},"o":{"a":0,"k":100,"ix":7},"sk":{"a":0,"k":0,"ix":4},"sa":{"a":0,"k":0,"ix":5},"nm":"Transformar"}],"nm":"Grupo 3","np":4,"cix":2,"bm":0,"ix":3,"mn":"ADBE Vector Group","hd":false}],"ip":0,"op":91,"st":0,"bm":0},{"ddd":0,"ind":2,"ty":4,"nm":"Capa 4/Iconos_limpios contornos 5","sr":1,"ks":{"o":{"a":0,"k":100,"ix":11},"r":{"a":0,"k":0,"ix":10},"p":{"a":1,"k":[{"i":{"x":0.71,"y":0.388},"o":{"x":0.387,"y":0},"t":0,"s":[143,112,0],"e":[131.125,101.208,0],"to":[-7.5,0,0],"ti":[0.063,2.708,0]},{"i":{"x":0.68,"y":0.626},"o":{"x":0.351,"y":0.285},"t":7.744,"s":[131.125,101.208,0],"e":[143,88,0],"to":[-0.063,-2.708,0],"ti":[-10.25,-0.5,0]},{"i":{"x":0.67,"y":0.652},"o":{"x":0.339,"y":0.314},"t":11.191,"s":[143,88,0],"e":[154.5,101.333,0],"to":[10.25,0.5,0],"ti":[0.5,-4.917,0]},{"i":{"x":0.663,"y":0.664},"o":{"x":0.332,"y":0.328},"t":13.926,"s":[154.5,101.333,0],"e":[143,112,0],"to":[-0.625,5.292,0],"ti":[7.5,0,0]},{"i":{"x":0.658,"y":0.672},"o":{"x":0.327,"y":0.336},"t":16.135,"s":[143,112,0],"e":[131.125,101.208,0],"to":[-7.5,0,0],"ti":[0.063,2.708,0]},{"i":{"x":0.65,"y":0.686},"o":{"x":0.319,"y":0.348},"t":18.409,"s":[131.125,101.208,0],"e":[143,88,0],"to":[-0.063,-2.708,0],"ti":[-10.25,-0.5,0]},{"i":{"x":0.64,"y":0.716},"o":{"x":0.31,"y":0.375},"t":21.402,"s":[143,88,0],"e":[154.5,101.333,0],"to":[10.25,0.5,0],"ti":[0.5,-4.917,0]},{"i":{"x":0.607,"y":1},"o":{"x":0.282,"y":0.612},"t":25.469,"s":[154.5,101.333,0],"e":[143,112,0],"to":[-0.625,5.292,0],"ti":[6.438,-0.156,0]},{"t":35}],"ix":2},"a":{"a":0,"k":[89,104.5,0],"ix":1},"s":{"a":0,"k":[100,100,100],"ix":6}},"ao":0,"shapes":[{"ty":"gr","it":[{"ind":0,"ty":"sh","ix":1,"ks":{"a":0,"k":{"i":[[0,0],[-0.01,-2.39],[-1.08,7.24],[-1.1,4.09],[0,0],[0,0],[-10.05,-0.84],[-1.8,-10.38],[0,0]],"o":[[0.13,3.07],[0.06,12.26],[0.23,-1.53],[-6.33,-2.69],[0,0],[3.53,-9.92],[10.04,0.85],[0,0],[0,0]],"v":[[24.77,30.55],[24.99,38.84],[-26.62,35.94],[-24.51,27.12],[-39.36,18.27],[-15.06,-35.64],[8.67,-50.26],[29.62,-31.88],[39.36,28.8]],"c":true},"ix":2},"nm":"Trazado 1","mn":"ADBE Vector Shape - Group","hd":false},{"ty":"st","c":{"a":0,"k":[1,1,1,1],"ix":3},"o":{"a":0,"k":100,"ix":4},"w":{"a":0,"k":1,"ix":5},"lc":2,"lj":2,"bm":0,"nm":"Trazo 1","mn":"ADBE Vector Graphic - Stroke","hd":false},{"ty":"tr","p":{"a":0,"k":[79.764,142.428],"ix":2},"a":{"a":0,"k":[0,0],"ix":1},"s":{"a":0,"k":[100,100],"ix":3},"r":{"a":0,"k":0,"ix":6},"o":{"a":0,"k":100,"ix":7},"sk":{"a":0,"k":0,"ix":4},"sa":{"a":0,"k":0,"ix":5},"nm":"Transformar"}],"nm":"Grupo 7","np":2,"cix":2,"bm":0,"ix":1,"mn":"ADBE Vector Group","hd":false},{"ty":"gr","it":[{"ind":0,"ty":"sh","ix":1,"ks":{"a":0,"k":{"i":[[0,0],[1.081,-7.241],[0.061,12.256],[0,0]],"o":[[0,0],[-1.081,7.242],[-0.079,-15.77],[0,0]],"v":[[-10.71,-33.447],[-25.294,18.293],[26.314,21.191],[23.277,-29.15]],"c":false},"ix":2},"nm":"Trazado 1","mn":"ADBE Vector Shape - Group","hd":false},{"ty":"st","c":{"a":0,"k":[1,1,1,1],"ix":3},"o":{"a":0,"k":100,"ix":4},"w":{"a":0,"k":1,"ix":5},"lc":2,"lj":2,"bm":0,"nm":"Trazo 1","mn":"ADBE Vector Graphic - Stroke","hd":false},{"ty":"tr","p":{"a":0,"k":[78.432,160.076],"ix":2},"a":{"a":0,"k":[0,0],"ix":1},"s":{"a":0,"k":[100,100],"ix":3},"r":{"a":0,"k":0,"ix":6},"o":{"a":0,"k":100,"ix":7},"sk":{"a":0,"k":0,"ix":4},"sa":{"a":0,"k":0,"ix":5},"nm":"Transformar"}],"nm":"Grupo 8","np":2,"cix":2,"bm":0,"ix":2,"mn":"ADBE Vector Group","hd":false},{"ty":"gr","it":[{"ind":0,"ty":"sh","ix":1,"ks":{"a":0,"k":{"i":[[0,0],[0,0],[0,0],[-10.047,-0.846],[-1.8,-10.378],[0,0],[0,0]],"o":[[-4.956,-1.839],[0,0],[3.536,-9.922],[10.046,0.845],[0,0],[0,0],[0,0]],"v":[[-24.433,37.311],[-39.36,28.421],[-15.067,-25.49],[8.665,-40.107],[29.619,-21.73],[39.36,38.947],[24.97,40.702]],"c":false},"ix":2},"nm":"Trazado 1","mn":"ADBE Vector Shape - Group","hd":false},{"ty":"st","c":{"a":0,"k":[1,1,1,1],"ix":3},"o":{"a":0,"k":100,"ix":4},"w":{"a":0,"k":1,"ix":5},"lc":2,"lj":2,"bm":0,"nm":"Trazo 1","mn":"ADBE Vector Graphic - Stroke","hd":false},{"ty":"tr","p":{"a":0,"k":[79.764,132.277],"ix":2},"a":{"a":0,"k":[0,0],"ix":1},"s":{"a":0,"k":[100,100],"ix":3},"r":{"a":0,"k":0,"ix":6},"o":{"a":0,"k":100,"ix":7},"sk":{"a":0,"k":0,"ix":4},"sa":{"a":0,"k":0,"ix":5},"nm":"Transformar"}],"nm":"Grupo 9","np":2,"cix":2,"bm":0,"ix":3,"mn":"ADBE Vector Group","hd":false}],"ip":0,"op":91,"st":0,"bm":0},{"ddd":0,"ind":3,"ty":4,"nm":"Capa 4/Iconos_limpios contornos 3","parent":2,"sr":1,"ks":{"o":{"a":0,"k":100,"ix":11},"r":{"a":0,"k":0,"ix":10},"p":{"a":0,"k":[110,169.5,0],"ix":2},"a":{"a":0,"k":[110,169.5,0],"ix":1},"s":{"a":0,"k":[100,100,100],"ix":6}},"ao":0,"hasMask":true,"masksProperties":[{"inv":false,"mode":"s","pt":{"a":0,"k":{"i":[[0,0],[-0.01,-2.39],[-1.08,7.24],[-1.1,4.09],[0,0],[0,0],[-10.05,-0.84],[-1.8,-10.38],[0,0]],"o":[[0.13,3.07],[0.06,12.26],[0.23,-1.53],[-6.33,-2.69],[0,0],[3.53,-9.92],[10.04,0.85],[0,0],[0,0]],"v":[[105.034,173.478],[105.254,181.768],[53.644,178.868],[55.754,170.048],[40.904,161.198],[65.204,107.288],[88.934,92.668],[109.884,111.048],[119.624,171.728]],"c":true},"ix":1},"o":{"a":0,"k":100,"ix":3},"x":{"a":0,"k":0,"ix":4},"nm":"Máscara 1"}],"shapes":[{"ty":"gr","it":[{"ind":0,"ty":"sh","ix":1,"ks":{"a":0,"k":{"i":[[0,0],[0,0],[0,0],[7.463,-1.978],[-2.697,-9.128],[0,0],[-27.285,-6.104],[-11.493,30.985],[0,0],[0,0],[8.323,1.861],[1.862,-8.323],[0,0],[8.323,1.862],[1.861,-8.324],[0,0],[8.323,1.861],[1.861,-8.323],[0,0]],"o":[[0,0],[0,0],[-3.763,-6.743],[-9.201,2.438],[0,0],[4.536,25.925],[33.149,7.414],[0,0],[0,0],[1.861,-8.323],[-8.323,-1.861],[0,0],[1.861,-8.323],[-8.322,-1.861],[0,0],[1.861,-8.323],[-8.322,-1.862],[0,0],[0,0]],"v":[[-23.477,-97.272],[-38.551,-29.876],[-54.04,-57.634],[-73.121,-65.733],[-84.995,-44.615],[-60.537,35.909],[-9.07,89.858],[68.461,47.777],[69.07,47.947],[85.832,-20.001],[74.133,-38.441],[55.691,-26.742],[58.1,-37.511],[46.401,-55.952],[27.961,-44.252],[30.213,-54.321],[18.513,-72.761],[0.073,-61.062],[7.116,-92.551]],"c":true},"ix":2},"nm":"Trazado 1","mn":"ADBE Vector Shape - Group","hd":false},{"ty":"st","c":{"a":0,"k":[1,1,1,1],"ix":3},"o":{"a":0,"k":100,"ix":4},"w":{"a":0,"k":1,"ix":5},"lc":1,"lj":2,"bm":0,"nm":"Trazo 1","mn":"ADBE Vector Graphic - Stroke","hd":false},{"ty":"tr","p":{"a":0,"k":[90.192,239.008],"ix":2},"a":{"a":0,"k":[0,0],"ix":1},"s":{"a":0,"k":[100,100],"ix":3},"r":{"a":0,"k":0,"ix":6},"o":{"a":0,"k":100,"ix":7},"sk":{"a":0,"k":0,"ix":4},"sa":{"a":0,"k":0,"ix":5},"nm":"Transformar"}],"nm":"Grupo 10","np":2,"cix":2,"bm":0,"ix":1,"mn":"ADBE Vector Group","hd":false}],"ip":0,"op":91,"st":0,"bm":0},{"ddd":0,"ind":4,"ty":4,"nm":"Capa 4/Iconos_limpios contornos 2","sr":1,"ks":{"o":{"a":0,"k":100,"ix":11},"r":{"a":0,"k":0,"ix":10},"p":{"a":0,"k":[164,177,0],"ix":2},"a":{"a":0,"k":[110,169.5,0],"ix":1},"s":{"a":0,"k":[100,100,100],"ix":6}},"ao":0,"hasMask":true,"masksProperties":[{"inv":false,"mode":"s","pt":{"a":1,"k":[{"i":{"x":0.833,"y":0.833},"o":{"x":0.167,"y":0.167},"t":0,"s":[{"i":[[0,0],[-0.01,-2.39],[-1.08,7.24],[-1.1,4.09],[0,0],[0,0],[-10.05,-0.84],[-1.8,-10.38],[0,0]],"o":[[0.13,3.07],[0.06,12.26],[0.23,-1.53],[-6.33,-2.69],[0,0],[3.53,-9.92],[10.04,0.85],[0,0],[0,0]],"v":[[105.034,173.478],[105.254,181.768],[53.644,178.868],[55.754,170.048],[40.904,161.198],[65.204,107.288],[88.934,92.668],[109.884,111.048],[119.624,171.728]],"c":true}],"e":[{"i":[[0,0],[-0.012,-2.39],[-1.088,7.239],[-1.1,4.09],[0,0],[0,0],[-10.049,-0.851],[-1.8,-10.38],[0,0]],"o":[[0.13,3.07],[0.06,12.26],[0.23,-1.53],[-6.33,-2.69],[0,0],[3.53,-9.92],[10.04,0.85],[0,0],[0,0]],"v":[[102.066,173.212],[102.286,181.502],[50.676,178.602],[52.786,169.782],[37.936,160.932],[62.236,107.022],[85.966,92.402],[106.916,110.782],[116.656,171.462]],"c":true}]},{"i":{"x":0.833,"y":0.833},"o":{"x":0.167,"y":0.167},"t":3.182,"s":[{"i":[[0,0],[-0.012,-2.39],[-1.088,7.239],[-1.1,4.09],[0,0],[0,0],[-10.049,-0.851],[-1.8,-10.38],[0,0]],"o":[[0.13,3.07],[0.06,12.26],[0.23,-1.53],[-6.33,-2.69],[0,0],[3.53,-9.92],[10.04,0.85],[0,0],[0,0]],"v":[[102.066,173.212],[102.286,181.502],[50.676,178.602],[52.786,169.782],[37.936,160.932],[62.236,107.022],[85.966,92.402],[106.916,110.782],[116.656,171.462]],"c":true}],"e":[{"i":[[0,0],[-0.012,-2.39],[-1.088,7.239],[-1.1,4.09],[0,0],[0,0],[-10.049,-0.851],[-1.8,-10.38],[0,0]],"o":[[0.13,3.07],[0.06,12.26],[0.23,-1.53],[-6.33,-2.69],[0,0],[3.53,-9.92],[10.04,0.85],[0,0],[0,0]],"v":[[97.755,171.367],[97.975,179.657],[46.365,176.757],[48.475,167.937],[33.625,159.087],[57.925,105.177],[81.655,90.557],[102.605,108.937],[112.345,169.617]],"c":true}]},{"i":{"x":0.833,"y":0.833},"o":{"x":0.167,"y":0.167},"t":5.303,"s":[{"i":[[0,0],[-0.012,-2.39],[-1.088,7.239],[-1.1,4.09],[0,0],[0,0],[-10.049,-0.851],[-1.8,-10.38],[0,0]],"o":[[0.13,3.07],[0.06,12.26],[0.23,-1.53],[-6.33,-2.69],[0,0],[3.53,-9.92],[10.04,0.85],[0,0],[0,0]],"v":[[97.755,171.367],[97.975,179.657],[46.365,176.757],[48.475,167.937],[33.625,159.087],[57.925,105.177],[81.655,90.557],[102.605,108.937],[112.345,169.617]],"c":true}],"e":[{"i":[[0,0],[-0.012,-2.39],[-1.088,7.239],[-1.1,4.09],[0,0],[0,0],[-10.049,-0.851],[-1.8,-10.38],[0,0]],"o":[[0.13,3.07],[0.06,12.26],[0.23,-1.53],[-6.33,-2.69],[0,0],[3.53,-9.92],[10.04,0.85],[0,0],[0,0]],"v":[[93.443,163.523],[93.663,171.813],[42.053,168.913],[44.163,160.093],[29.313,151.243],[53.613,97.333],[77.343,82.713],[98.293,101.093],[108.033,161.773]],"c":true}]},{"i":{"x":0.833,"y":0.833},"o":{"x":0.167,"y":0.167},"t":7.424,"s":[{"i":[[0,0],[-0.012,-2.39],[-1.088,7.239],[-1.1,4.09],[0,0],[0,0],[-10.049,-0.851],[-1.8,-10.38],[0,0]],"o":[[0.13,3.07],[0.06,12.26],[0.23,-1.53],[-6.33,-2.69],[0,0],[3.53,-9.92],[10.04,0.85],[0,0],[0,0]],"v":[[93.443,163.523],[93.663,171.813],[42.053,168.913],[44.163,160.093],[29.313,151.243],[53.613,97.333],[77.343,82.713],[98.293,101.093],[108.033,161.773]],"c":true}],"e":[{"i":[[0,0],[-0.012,-2.39],[-1.088,7.239],[-1.1,4.09],[0,0],[0,0],[-10.049,-0.851],[-1.8,-10.38],[0,0]],"o":[[0.13,3.07],[0.06,12.26],[0.23,-1.53],[-6.33,-2.69],[0,0],[3.53,-9.92],[10.04,0.85],[0,0],[0,0]],"v":[[95.738,154.251],[95.958,162.541],[44.348,159.641],[46.458,150.821],[31.608,141.971],[55.908,88.061],[79.638,73.441],[100.588,91.821],[110.328,152.501]],"c":true}]},{"i":{"x":0.833,"y":0.833},"o":{"x":0.167,"y":0.167},"t":9.546,"s":[{"i":[[0,0],[-0.012,-2.39],[-1.088,7.239],[-1.1,4.09],[0,0],[0,0],[-10.049,-0.851],[-1.8,-10.38],[0,0]],"o":[[0.13,3.07],[0.06,12.26],[0.23,-1.53],[-6.33,-2.69],[0,0],[3.53,-9.92],[10.04,0.85],[0,0],[0,0]],"v":[[95.738,154.251],[95.958,162.541],[44.348,159.641],[46.458,150.821],[31.608,141.971],[55.908,88.061],[79.638,73.441],[100.588,91.821],[110.328,152.501]],"c":true}],"e":[{"i":[[0,0],[-0.012,-2.39],[-1.088,7.239],[-1.1,4.09],[0,0],[0,0],[-10.049,-0.851],[-1.8,-10.38],[0,0]],"o":[[0.13,3.07],[0.06,12.26],[0.23,-1.53],[-6.33,-2.69],[0,0],[3.53,-9.92],[10.04,0.85],[0,0],[0,0]],"v":[[108.034,149.978],[108.254,158.268],[56.644,155.368],[58.754,146.548],[43.904,137.698],[68.204,83.788],[91.934,69.168],[112.884,87.548],[122.624,148.228]],"c":true}]},{"i":{"x":0.833,"y":0.833},"o":{"x":0.167,"y":0.167},"t":11.667,"s":[{"i":[[0,0],[-0.012,-2.39],[-1.088,7.239],[-1.1,4.09],[0,0],[0,0],[-10.049,-0.851],[-1.8,-10.38],[0,0]],"o":[[0.13,3.07],[0.06,12.26],[0.23,-1.53],[-6.33,-2.69],[0,0],[3.53,-9.92],[10.04,0.85],[0,0],[0,0]],"v":[[108.034,149.978],[108.254,158.268],[56.644,155.368],[58.754,146.548],[43.904,137.698],[68.204,83.788],[91.934,69.168],[112.884,87.548],[122.624,148.228]],"c":true}],"e":[{"i":[[0,0],[-0.012,-2.39],[-1.088,7.239],[-1.1,4.09],[0,0],[0,0],[-10.049,-0.851],[-1.8,-10.38],[0,0]],"o":[[0.13,3.07],[0.06,12.26],[0.23,-1.53],[-6.33,-2.69],[0,0],[3.53,-9.92],[10.04,0.85],[0,0],[0,0]],"v":[[116.534,162.728],[116.754,171.018],[65.144,168.118],[67.254,159.298],[52.404,150.448],[76.704,96.538],[100.434,81.918],[121.384,100.298],[131.124,160.978]],"c":true}]},{"i":{"x":0.833,"y":0.833},"o":{"x":0.167,"y":0.167},"t":13.788,"s":[{"i":[[0,0],[-0.012,-2.39],[-1.088,7.239],[-1.1,4.09],[0,0],[0,0],[-10.049,-0.851],[-1.8,-10.38],[0,0]],"o":[[0.13,3.07],[0.06,12.26],[0.23,-1.53],[-6.33,-2.69],[0,0],[3.53,-9.92],[10.04,0.85],[0,0],[0,0]],"v":[[116.534,162.728],[116.754,171.018],[65.144,168.118],[67.254,159.298],[52.404,150.448],[76.704,96.538],[100.434,81.918],[121.384,100.298],[131.124,160.978]],"c":true}],"e":[{"i":[[0,0],[-0.01,-2.39],[-1.08,7.24],[-1.1,4.09],[0,0],[0,0],[-10.05,-0.84],[-1.8,-10.38],[0,0]],"o":[[0.13,3.07],[0.06,12.26],[0.23,-1.53],[-6.33,-2.69],[0,0],[3.53,-9.92],[10.04,0.85],[0,0],[0,0]],"v":[[105.034,173.478],[105.254,181.768],[53.644,178.868],[55.754,170.048],[40.904,161.198],[65.204,107.288],[88.934,92.668],[109.884,111.048],[119.624,171.728]],"c":true}]},{"i":{"x":0.833,"y":0.833},"o":{"x":0.167,"y":0.167},"t":15.909,"s":[{"i":[[0,0],[-0.01,-2.39],[-1.08,7.24],[-1.1,4.09],[0,0],[0,0],[-10.05,-0.84],[-1.8,-10.38],[0,0]],"o":[[0.13,3.07],[0.06,12.26],[0.23,-1.53],[-6.33,-2.69],[0,0],[3.53,-9.92],[10.04,0.85],[0,0],[0,0]],"v":[[105.034,173.478],[105.254,181.768],[53.644,178.868],[55.754,170.048],[40.904,161.198],[65.204,107.288],[88.934,92.668],[109.884,111.048],[119.624,171.728]],"c":true}],"e":[{"i":[[0,0],[-0.012,-2.39],[-1.088,7.239],[-1.1,4.09],[0,0],[0,0],[-10.049,-0.851],[-1.8,-10.38],[0,0]],"o":[[0.13,3.07],[0.06,12.26],[0.23,-1.53],[-6.33,-2.69],[0,0],[3.53,-9.92],[10.04,0.85],[0,0],[0,0]],"v":[[93.034,165.978],[93.254,174.268],[41.644,171.368],[43.754,162.548],[28.904,153.698],[53.204,99.788],[76.934,85.168],[97.884,103.548],[107.624,164.228]],"c":true}]},{"i":{"x":0.833,"y":0.833},"o":{"x":0.167,"y":0.167},"t":18.03,"s":[{"i":[[0,0],[-0.012,-2.39],[-1.088,7.239],[-1.1,4.09],[0,0],[0,0],[-10.049,-0.851],[-1.8,-10.38],[0,0]],"o":[[0.13,3.07],[0.06,12.26],[0.23,-1.53],[-6.33,-2.69],[0,0],[3.53,-9.92],[10.04,0.85],[0,0],[0,0]],"v":[[93.034,165.978],[93.254,174.268],[41.644,171.368],[43.754,162.548],[28.904,153.698],[53.204,99.788],[76.934,85.168],[97.884,103.548],[107.624,164.228]],"c":true}],"e":[{"i":[[0,0],[-0.012,-2.39],[-1.088,7.239],[-1.1,4.09],[0,0],[0,0],[-10.049,-0.851],[-1.8,-10.38],[0,0]],"o":[[0.13,3.07],[0.06,12.26],[0.23,-1.53],[-6.33,-2.69],[0,0],[3.53,-9.92],[10.04,0.85],[0,0],[0,0]],"v":[[98.367,151.915],[98.587,160.205],[46.977,157.305],[49.087,148.485],[34.237,139.635],[58.537,85.725],[82.267,71.105],[103.217,89.485],[112.957,150.165]],"c":true}]},{"i":{"x":0.833,"y":0.833},"o":{"x":0.167,"y":0.167},"t":20.151,"s":[{"i":[[0,0],[-0.012,-2.39],[-1.088,7.239],[-1.1,4.09],[0,0],[0,0],[-10.049,-0.851],[-1.8,-10.38],[0,0]],"o":[[0.13,3.07],[0.06,12.26],[0.23,-1.53],[-6.33,-2.69],[0,0],[3.53,-9.92],[10.04,0.85],[0,0],[0,0]],"v":[[98.367,151.915],[98.587,160.205],[46.977,157.305],[49.087,148.485],[34.237,139.635],[58.537,85.725],[82.267,71.105],[103.217,89.485],[112.957,150.165]],"c":true}],"e":[{"i":[[0,0],[-0.012,-2.39],[-1.088,7.239],[-1.1,4.09],[0,0],[0,0],[-10.049,-0.851],[-1.8,-10.38],[0,0]],"o":[[0.13,3.07],[0.06,12.26],[0.23,-1.53],[-6.33,-2.69],[0,0],[3.53,-9.92],[10.04,0.85],[0,0],[0,0]],"v":[[103.284,149.384],[103.504,157.674],[51.894,154.774],[54.004,145.954],[39.154,137.104],[63.454,83.194],[87.184,68.574],[108.134,86.954],[117.874,147.634]],"c":true}]},{"i":{"x":0.833,"y":0.833},"o":{"x":0.167,"y":0.167},"t":21.212,"s":[{"i":[[0,0],[-0.012,-2.39],[-1.088,7.239],[-1.1,4.09],[0,0],[0,0],[-10.049,-0.851],[-1.8,-10.38],[0,0]],"o":[[0.13,3.07],[0.06,12.26],[0.23,-1.53],[-6.33,-2.69],[0,0],[3.53,-9.92],[10.04,0.85],[0,0],[0,0]],"v":[[103.284,149.384],[103.504,157.674],[51.894,154.774],[54.004,145.954],[39.154,137.104],[63.454,83.194],[87.184,68.574],[108.134,86.954],[117.874,147.634]],"c":true}],"e":[{"i":[[0,0],[-0.012,-2.39],[-1.088,7.239],[-1.1,4.09],[0,0],[0,0],[-10.049,-0.851],[-1.8,-10.38],[0,0]],"o":[[0.13,3.07],[0.06,12.26],[0.23,-1.53],[-6.33,-2.69],[0,0],[3.53,-9.92],[10.04,0.85],[0,0],[0,0]],"v":[[114.303,153.091],[114.523,161.381],[62.913,158.481],[65.023,149.661],[50.173,140.811],[74.473,86.901],[98.203,72.281],[119.153,90.661],[128.893,151.341]],"c":true}]},{"i":{"x":0.833,"y":0.833},"o":{"x":0.167,"y":0.167},"t":23.333,"s":[{"i":[[0,0],[-0.012,-2.39],[-1.088,7.239],[-1.1,4.09],[0,0],[0,0],[-10.049,-0.851],[-1.8,-10.38],[0,0]],"o":[[0.13,3.07],[0.06,12.26],[0.23,-1.53],[-6.33,-2.69],[0,0],[3.53,-9.92],[10.04,0.85],[0,0],[0,0]],"v":[[114.303,153.091],[114.523,161.381],[62.913,158.481],[65.023,149.661],[50.173,140.811],[74.473,86.901],[98.203,72.281],[119.153,90.661],[128.893,151.341]],"c":true}],"e":[{"i":[[0,0],[-0.012,-2.39],[-1.088,7.239],[-1.1,4.09],[0,0],[0,0],[-10.049,-0.851],[-1.8,-10.38],[0,0]],"o":[[0.13,3.07],[0.06,12.26],[0.23,-1.53],[-6.33,-2.69],[0,0],[3.53,-9.92],[10.04,0.85],[0,0],[0,0]],"v":[[116.322,162.798],[116.542,171.088],[64.932,168.188],[67.042,159.368],[52.192,150.518],[76.492,96.608],[100.222,81.988],[121.172,100.368],[130.912,161.048]],"c":true}]},{"i":{"x":0.833,"y":0.833},"o":{"x":0.167,"y":0.167},"t":25.454,"s":[{"i":[[0,0],[-0.012,-2.39],[-1.088,7.239],[-1.1,4.09],[0,0],[0,0],[-10.049,-0.851],[-1.8,-10.38],[0,0]],"o":[[0.13,3.07],[0.06,12.26],[0.23,-1.53],[-6.33,-2.69],[0,0],[3.53,-9.92],[10.04,0.85],[0,0],[0,0]],"v":[[116.322,162.798],[116.542,171.088],[64.932,168.188],[67.042,159.368],[52.192,150.518],[76.492,96.608],[100.222,81.988],[121.172,100.368],[130.912,161.048]],"c":true}],"e":[{"i":[[0,0],[-0.012,-2.39],[-1.088,7.239],[-1.1,4.09],[0,0],[0,0],[-10.049,-0.851],[-1.8,-10.38],[0,0]],"o":[[0.13,3.07],[0.06,12.26],[0.23,-1.53],[-6.33,-2.69],[0,0],[3.53,-9.92],[10.04,0.85],[0,0],[0,0]],"v":[[113.314,168.921],[113.534,177.211],[61.924,174.311],[64.034,165.491],[49.184,156.641],[73.484,102.731],[97.214,88.111],[118.164,106.491],[127.904,167.171]],"c":true}]},{"i":{"x":0.833,"y":0.833},"o":{"x":0.167,"y":0.167},"t":27.576,"s":[{"i":[[0,0],[-0.012,-2.39],[-1.088,7.239],[-1.1,4.09],[0,0],[0,0],[-10.049,-0.851],[-1.8,-10.38],[0,0]],"o":[[0.13,3.07],[0.06,12.26],[0.23,-1.53],[-6.33,-2.69],[0,0],[3.53,-9.92],[10.04,0.85],[0,0],[0,0]],"v":[[113.314,168.921],[113.534,177.211],[61.924,174.311],[64.034,165.491],[49.184,156.641],[73.484,102.731],[97.214,88.111],[118.164,106.491],[127.904,167.171]],"c":true}],"e":[{"i":[[0,0],[-0.012,-2.39],[-1.088,7.239],[-1.1,4.09],[0,0],[0,0],[-10.049,-0.851],[-1.8,-10.38],[0,0]],"o":[[0.13,3.07],[0.06,12.26],[0.23,-1.53],[-6.33,-2.69],[0,0],[3.53,-9.92],[10.04,0.85],[0,0],[0,0]],"v":[[109.305,172.044],[109.525,180.334],[57.915,177.434],[60.025,168.614],[45.175,159.764],[69.475,105.854],[93.205,91.234],[114.155,109.614],[123.895,170.294]],"c":true}]},{"i":{"x":0.833,"y":0.833},"o":{"x":0.167,"y":0.167},"t":29.697,"s":[{"i":[[0,0],[-0.012,-2.39],[-1.088,7.239],[-1.1,4.09],[0,0],[0,0],[-10.049,-0.851],[-1.8,-10.38],[0,0]],"o":[[0.13,3.07],[0.06,12.26],[0.23,-1.53],[-6.33,-2.69],[0,0],[3.53,-9.92],[10.04,0.85],[0,0],[0,0]],"v":[[109.305,172.044],[109.525,180.334],[57.915,177.434],[60.025,168.614],[45.175,159.764],[69.475,105.854],[93.205,91.234],[114.155,109.614],[123.895,170.294]],"c":true}],"e":[{"i":[[0,0],[-0.012,-2.39],[-1.088,7.239],[-1.1,4.09],[0,0],[0,0],[-10.049,-0.851],[-1.8,-10.38],[0,0]],"o":[[0.13,3.07],[0.06,12.26],[0.23,-1.53],[-6.33,-2.69],[0,0],[3.53,-9.92],[10.04,0.85],[0,0],[0,0]],"v":[[107.097,173.618],[107.317,181.908],[55.707,179.008],[57.817,170.188],[42.967,161.338],[67.267,107.428],[90.997,92.808],[111.947,111.188],[121.687,171.868]],"c":true}]},{"i":{"x":0.833,"y":0.833},"o":{"x":0.167,"y":0.167},"t":31.818,"s":[{"i":[[0,0],[-0.012,-2.39],[-1.088,7.239],[-1.1,4.09],[0,0],[0,0],[-10.049,-0.851],[-1.8,-10.38],[0,0]],"o":[[0.13,3.07],[0.06,12.26],[0.23,-1.53],[-6.33,-2.69],[0,0],[3.53,-9.92],[10.04,0.85],[0,0],[0,0]],"v":[[107.097,173.618],[107.317,181.908],[55.707,179.008],[57.817,170.188],[42.967,161.338],[67.267,107.428],[90.997,92.808],[111.947,111.188],[121.687,171.868]],"c":true}],"e":[{"i":[[0,0],[-0.01,-2.39],[-1.08,7.24],[-1.1,4.09],[0,0],[0,0],[-10.05,-0.84],[-1.8,-10.38],[0,0]],"o":[[0.13,3.07],[0.06,12.26],[0.23,-1.53],[-6.33,-2.69],[0,0],[3.53,-9.92],[10.04,0.85],[0,0],[0,0]],"v":[[105.034,173.478],[105.254,181.768],[53.644,178.868],[55.754,170.048],[40.904,161.198],[65.204,107.288],[88.934,92.668],[109.884,111.048],[119.624,171.728]],"c":true}]},{"t":35}],"ix":1},"o":{"a":0,"k":100,"ix":3},"x":{"a":0,"k":0,"ix":4},"nm":"Máscara 1"}],"shapes":[{"ty":"gr","it":[{"ind":0,"ty":"sh","ix":1,"ks":{"a":0,"k":{"i":[[9.466,0],[0,0],[0,9.466],[0,0],[-9.466,0],[0,-9.466],[0,0]],"o":[[0,0],[-9.466,0],[0,0],[0,-9.466],[9.466,0],[0,0],[0,9.466]],"v":[[0,28.851],[0,28.851],[-17.139,11.712],[-17.139,-11.712],[0,-28.851],[17.139,-11.712],[17.139,11.712]],"c":true},"ix":2},"nm":"Trazado 1","mn":"ADBE Vector Shape - Group","hd":false},{"ty":"st","c":{"a":0,"k":[1,1,1,1],"ix":3},"o":{"a":0,"k":100,"ix":4},"w":{"a":0,"k":1,"ix":5},"lc":1,"lj":2,"bm":0,"nm":"Trazo 1","mn":"ADBE Vector Graphic - Stroke","hd":false},{"ty":"tr","p":{"a":0,"k":[103.004,83.027],"ix":2},"a":{"a":0,"k":[0,0],"ix":1},"s":{"a":0,"k":[100,100],"ix":3},"r":{"a":0,"k":0,"ix":6},"o":{"a":0,"k":100,"ix":7},"sk":{"a":0,"k":0,"ix":4},"sa":{"a":0,"k":0,"ix":5},"nm":"Transformar"}],"nm":"Grupo 11","np":2,"cix":2,"bm":0,"ix":1,"mn":"ADBE Vector Group","hd":false},{"ty":"gr","it":[{"ind":0,"ty":"sh","ix":1,"ks":{"a":0,"k":{"i":[[0,-5.207],[5.207,0],[0,5.206],[-5.206,0]],"o":[[0,5.206],[-5.206,0],[0,-5.207],[5.207,0]],"v":[[9.427,0],[-0.001,9.426],[-9.427,0],[-0.001,-9.426]],"c":true},"ix":2},"nm":"Trazado 1","mn":"ADBE Vector Shape - Group","hd":false},{"ty":"st","c":{"a":0,"k":[1,1,1,1],"ix":3},"o":{"a":0,"k":100,"ix":4},"w":{"a":0,"k":1,"ix":5},"lc":1,"lj":2,"bm":0,"nm":"Trazo 1","mn":"ADBE Vector Graphic - Stroke","hd":false},{"ty":"tr","p":{"a":0,"k":[103.004,92.453],"ix":2},"a":{"a":0,"k":[0,0],"ix":1},"s":{"a":0,"k":[100,100],"ix":3},"r":{"a":0,"k":0,"ix":6},"o":{"a":0,"k":100,"ix":7},"sk":{"a":0,"k":0,"ix":4},"sa":{"a":0,"k":0,"ix":5},"nm":"Transformar"}],"nm":"Grupo 12","np":2,"cix":2,"bm":0,"ix":2,"mn":"ADBE Vector Group","hd":false},{"ty":"gr","it":[{"ind":0,"ty":"sh","ix":1,"ks":{"a":0,"k":{"i":[[0,-5.206],[5.207,0],[0,5.207],[-5.206,0]],"o":[[0,5.207],[-5.206,0],[0,-5.206],[5.207,0]],"v":[[9.427,-0.001],[-0.001,9.426],[-9.427,-0.001],[-0.001,-9.426]],"c":true},"ix":2},"nm":"Trazado 1","mn":"ADBE Vector Shape - Group","hd":false},{"ty":"st","c":{"a":0,"k":[1,1,1,1],"ix":3},"o":{"a":0,"k":100,"ix":4},"w":{"a":0,"k":1,"ix":5},"lc":1,"lj":2,"bm":0,"nm":"Trazo 1","mn":"ADBE Vector Graphic - Stroke","hd":false},{"ty":"tr","p":{"a":0,"k":[103.004,73.601],"ix":2},"a":{"a":0,"k":[0,0],"ix":1},"s":{"a":0,"k":[100,100],"ix":3},"r":{"a":0,"k":0,"ix":6},"o":{"a":0,"k":100,"ix":7},"sk":{"a":0,"k":0,"ix":4},"sa":{"a":0,"k":0,"ix":5},"nm":"Transformar"}],"nm":"Grupo 13","np":2,"cix":2,"bm":0,"ix":3,"mn":"ADBE Vector Group","hd":false},{"ty":"gr","it":[{"ind":0,"ty":"sh","ix":1,"ks":{"a":0,"k":{"i":[[0,0],[0,0],[-8.871,0],[0,0],[0,-9.518],[0,0]],"o":[[0,0],[0,-9.518],[0,0],[8.872,0],[0,0],[0,0]],"v":[[-73.532,-14.054],[-73.532,-81.574],[-57.47,-98.808],[57.468,-98.808],[73.532,-81.574],[73.532,98.808]],"c":false},"ix":2},"nm":"Trazado 1","mn":"ADBE Vector Shape - Group","hd":false},{"ty":"st","c":{"a":0,"k":[1,1,1,1],"ix":3},"o":{"a":0,"k":100,"ix":4},"w":{"a":0,"k":1,"ix":5},"lc":1,"lj":2,"bm":0,"nm":"Trazo 1","mn":"ADBE Vector Graphic - Stroke","hd":false},{"ty":"tr","p":{"a":0,"k":[143.023,128.117],"ix":2},"a":{"a":0,"k":[0,0],"ix":1},"s":{"a":0,"k":[100,100],"ix":3},"r":{"a":0,"k":0,"ix":6},"o":{"a":0,"k":100,"ix":7},"sk":{"a":0,"k":0,"ix":4},"sa":{"a":0,"k":0,"ix":5},"nm":"Transformar"}],"nm":"Grupo 14","np":2,"cix":2,"bm":0,"ix":4,"mn":"ADBE Vector Group","hd":false}],"ip":0,"op":91,"st":0,"bm":0}],"markers":[]}